dbtest/main.py
dbtest-0.1.0.dist-info/LICENSE
dbtest-0.1.0.dist-info/WHEEL
dbtest-0.1.0.dist-info/METADATA
dbtest-0.1.0.dist-info/RECORD
